{
    "meta": {
        "format_version": 2,
        "name": "Pesterchum theme repository"
    },
    "entries": [
        {
            "name": "trollian2.5dark",
            "author": "(lis)anne",
            "client": "pesterchum",
            "download": "https://raw.githubusercontent.com/mocchapi/pesterchum-themes/main/themes/pesterchum/trollian2.5dark.zip",
            "inherits": "trollian2.5",
            "version": 2,
            "updated": 1689282706,
            "source": "https://github.com/mocchapi/pesterchum-themes",
            "description": "Trollian 2.5 but with a dark chat background",
            "sha256_download": "35cd55229069eac66c10ffe963dccfb64dd1073685f5a13710139821f430f39b",
            "sha256_install": "4bed376c97a7865ba9711f8e86e15576ac7318aaaf52244928b5e4d5d1f0c21f"
        },
        {
            "name": "pchum95Plus!",
            "author": "matytoonist",
            "client": "pesterchum",
            "download": "https://raw.githubusercontent.com/mocchapi/pesterchum-themes/main/themes/pesterchum/pchum95Plus!.zip",
            "inherits": "",
            "version": 0,
            "updated": 1683470882,
            "source": "https://github.com/mocchapi/pesterchum-themes",
            "description": "Windows 95 Plus! inspired theme",
            "sha256_download": "54f7175fb72462378161509a695d4bcbc69ec90f7e4b3427546c74d1fc0af096",
            "sha256_install": "ffa84c26903c8d9fbfae6d048a6039853f4aa698e02efc10c15309cce0fcbdd4"
        },
        {
            "name": "trollian95",
            "author": "matytoonist",
            "client": "pesterchum",
            "download": "https://raw.githubusercontent.com/mocchapi/pesterchum-themes/main/themes/pesterchum/trollian95.zip",
            "inherits": "",
            "version": 0,
            "updated": 1683478448,
            "source": "https://github.com/mocchapi/pesterchum-themes",
            "description": "Windows 95 inspired trollian theme",
            "sha256_download": "988ff74cdfa7d5818ade0d940f2ef4d937c1dc298e4e88d321042f908cd0ef6a",
            "sha256_install": "64d8b233c5e8dfc3a38e89a2941d01a80e7a62551b6a4f053ed3336469ca0652"
        },
        {
            "name": "trollian95Plus!",
            "author": "matytoonist",
            "client": "pesterchum",
            "download": "https://raw.githubusercontent.com/mocchapi/pesterchum-themes/main/themes/pesterchum/trollian95Plus!.zip",
            "inherits": "",
            "version": 0,
            "updated": 1683097026,
            "source": "https://github.com/mocchapi/pesterchum-themes",
            "description": "Windows 95 Plus! inspired trollian theme",
            "sha256_download": "33458ec98343597f1aa795571e1b1c8c211f4609c36ada44592df2298d3ed7fd",
            "sha256_install": "06cb700998c704ac003d1b272b4ecc8397d0d389e943b1ff8b61ddedaa6cd4b7"
        },
        {
            "name": "pibby",
            "author": "mal",
            "client": "pesterchum",
            "download": "https://raw.githubusercontent.com/mocchapi/pesterchum-themes/main/themes/pesterchum/pibby.zip",
            "inherits": "",
            "version": 0,
            "updated": 1679420446,
            "source": "https://github.com/mocchapi/pesterchum-themes",
            "description": "el gato. Requires this font: https://www.dafont.com/austie-bost-kitten-klub.font",
            "sha256_download": "6067a75da25ac0b39fb029d02fad651ef89d1943b08418f56f3db4f62e9c9d71",
            "sha256_install": "a33b453f1332cce03c2981297f2e4ee833d8b1207518aebd0a8cfb0a5f9f8e2e"
        },
        {
            "name": "pesterchum2.5dark",
            "author": "(lis)anne",
            "client": "pesterchum",
            "download": "https://raw.githubusercontent.com/mocchapi/pesterchum-themes/main/themes/pesterchum/pesterchum2.5dark.zip",
            "inherits": "pesterchum2.5",
            "version": 4,
            "updated": 1689366830,
            "source": "https://github.com/mocchapi/pesterchum-themes",
            "description": "Pesterchum 2.5, but with dark chat backgrounds",
            "sha256_download": "9e5595b64b3d4caaa338aac5442dd00d09762711c12f70dcda4f007475d186b0",
            "sha256_install": "8f7919fad4795e75b13987e669997f1ed48415182938ccb9bcfc7d6c1ed6eb42"
        },
        {
            "name": "gec",
            "author": "URAYsan",
            "client": "pesterchum",
            "download": "https://raw.githubusercontent.com/mocchapi/pesterchum-themes/main/themes/pesterchum/gec.zip",
            "inherits": "",
            "version": 1,
            "updated": 1682422088,
            "source": "https://github.com/mocchapi/pesterchum-themes",
            "description": "100 gecs theme",
            "sha256_download": "6b9ab51d0e35459d7ee871accfc1a2b58286d0b5b739b7156b5e597c3a131772",
            "sha256_install": "0a8884b3cd118ac7574e373d481ec5cd13f5ad1493440eecded7799cc11d8f6a"
        },
        {
            "name": "gec xl",
            "author": "URAYsan",
            "client": "pesterchum",
            "download": "https://raw.githubusercontent.com/mocchapi/pesterchum-themes/main/themes/pesterchum/gec xl.zip",
            "inherits": "gec",
            "version": 1,
            "updated": 1679352702,
            "source": "https://github.com/mocchapi/pesterchum-themes",
            "description": "100 gecs theme, but bigger",
            "sha256_download": "a5f43516d814f82ab72c0ea3b09e58a45237cd8de65dd5d54cdce9edc1c247fe",
            "sha256_install": "386558d6d6c2eb53ddecf59a755723260f8c0540d7e1c197cfe8e9572b89682b"
        },
        {
            "name": "TruestTrollian",
            "author": "mal",
            "client": "pesterchum",
            "download": "https://raw.githubusercontent.com/mocchapi/pesterchum-themes/main/themes/pesterchum/TruestTrollian.zip",
            "inherits": "",
            "version": 0,
            "updated": 1686430232,
            "source": "https://github.com/mocchapi/pesterchum-themes",
            "description": "Trollian in alternian. requires this font: https://trolltype.mspa.sudrien.net/alternian.ttf",
            "sha256_download": "9f990217da09e7498af72fe4fe694e5fe0cc0ec601d6a9955a279ee59fc0b576",
            "sha256_install": "782503eb960af1e6f308c5f616cdd1aba697fe96c63b20cb56d7722f68422190"
        },
        {
            "name": "Skaianet Systems Terminal",
            "author": "mal",
            "client": "pesterchum",
            "download": "https://raw.githubusercontent.com/mocchapi/pesterchum-themes/main/themes/pesterchum/Skaianet Systems Terminal.zip",
            "inherits": "",
            "version": 2,
            "updated": 1687371053,
            "source": "https://github.com/mocchapi/pesterchum-themes",
            "description": "Terminal theme. Requires the included dejavu mono font to be installed",
            "sha256_download": "a2c34e35bc5e112c9da58779ba622cfc0045d8e4121f8227eb98c32ec45a79fb",
            "sha256_install": "707159a2e7b5c4f348f7fdb6c85723c206816fe5db6799551f24bc2c04aaa2b7"
        },
        {
            "name": "JEERUBIUM",
            "author": "mal",
            "client": "pesterchum",
            "download": "https://raw.githubusercontent.com/mocchapi/pesterchum-themes/main/themes/pesterchum/JEERUBIUM.zip",
            "inherits": "",
            "version": 2,
            "updated": 1691446939,
            "source": "https://github.com/mocchapi/pesterchum-themes",
            "description": "An imagining of the client Caliborn used, with personalised stickers & sketches",
            "sha256_download": "ae34473cda19c69193cc6ab88f0f6f7bbc454f59150a89ed74e05821b5f7008f",
            "sha256_install": "d16a4634266c57f3cb9164d8279ff070ddb367ca2921c8fbb0d84cfc3ca209ad"
        },
        {
            "name": "JEERUBIUM REDUX",
            "author": "mal",
            "client": "pesterchum",
            "download": "https://raw.githubusercontent.com/mocchapi/pesterchum-themes/main/themes/pesterchum/JEERUBIUM REDUX.zip",
            "inherits": "",
            "version": 1,
            "updated": 1691446541,
            "source": "https://github.com/mocchapi/pesterchum-themes",
            "description": "An imagining of the client Caliborn used, without personalised stickers & sketches",
            "sha256_download": "138e01645a6be35484ae5a1ff7e7b5f455c5a75923124a59c5feff1ed241d504",
            "sha256_install": "69037c9f37d301555d6ca9ae012822fd30590ea1369aff6a94338d705d51eeb6"
        },
        {
            "name": "CHEERUBIUM",
            "author": "mal",
            "client": "pesterchum",
            "download": "https://raw.githubusercontent.com/mocchapi/pesterchum-themes/main/themes/pesterchum/CHEERUBIUM.zip",
            "inherits": "",
            "version": 1,
            "updated": 1691446483,
            "source": "https://github.com/mocchapi/pesterchum-themes",
            "description": "An imagining of the client Calliope used, with personalised stickers & sketches",
            "sha256_download": "94aa075a6eab779e8bd399a96190e16cd537c159b9ab5e21e444d7d600797ff4",
            "sha256_install": "e3ffbff3b0aa9dc8b41dc95e6e573fae631e95b180c106c9c6f1b7713685db21"
        },
        {
            "name": "CHEERUBIUM REDUX",
            "author": "mal",
            "client": "pesterchum",
            "download": "https://raw.githubusercontent.com/mocchapi/pesterchum-themes/main/themes/pesterchum/CHEERUBIUM REDUX.zip",
            "inherits": "",
            "version": 1,
            "updated": 1691446521,
            "source": "https://github.com/mocchapi/pesterchum-themes",
            "description": "An imagining of the client Calliope, without personalised stickers & sketches",
            "sha256_download": "bd4532ec0309815a8ae6ff50cfa08efe248dbc733e735e1b28ddaf1368c14832",
            "sha256_install": "656e4342f1c58ef84597fe31ee0731799b070f19ec4c4583059e2c2ff6429f70"
        },
        {
            "name": "vriskachum",
            "author": "Demadunk",
            "client": "pesterchum",
            "download": "https://raw.githubusercontent.com/mocchapi/pesterchum-themes/main/themes/pesterchum/vriskachum.zip",
            "inherits": "",
            "version": 0,
            "updated": 1459786678,
            "source": "https://github.com/mocchapi/pesterchum-themes",
            "description": "Very blue. Vriska theme",
            "sha256_download": "cecb805d8fadd8108cea1919bc897d3010d16d333ceae8a766043d7360621018",
            "sha256_install": "c323cd089f742b23b915c0e43d9987699691b79f5ab6eacf0840bb24f2f9e196"
        },
        {
            "name": "araneachum",
            "author": "Demadunk",
            "client": "pesterchum",
            "download": "https://raw.githubusercontent.com/mocchapi/pesterchum-themes/main/themes/pesterchum/araneachum.zip",
            "inherits": "",
            "version": 0,
            "updated": 1465325456,
            "source": "https://github.com/mocchapi/pesterchum-themes",
            "description": "Similar to vriskachum, but lighter. Aranea theme",
            "sha256_download": "fab9179c5fd6dfedd74b848fad255cf306eca9dd3b5f890ccec7f6ae06d8c4bb",
            "sha256_install": "2e06d1ff3916c6a96de82ed1232ffee65a9337c43ce6d8c81b2e8fc8999dfcf8"
        },
        {
            "name": "strifekindRED",
            "author": "Demadunk",
            "client": "pesterchum",
            "download": "https://raw.githubusercontent.com/mocchapi/pesterchum-themes/main/themes/pesterchum/strifekindRED.zip",
            "inherits": "pesterchum2.5",
            "version": 0,
            "updated": 1453478134,
            "source": "https://github.com/mocchapi/pesterchum-themes",
            "description": "Strifekind, but red",
            "sha256_download": "de3de66b80719292f8b0e41a03b0767a21d1290368ddbf5e9913d7019b846528",
            "sha256_install": "2481ba45b5f40c84d710980e77f551a809e74ed7b87cc179c342148fac67375e"
        },
        {
            "name": "UTChum",
            "author": "Demadunk",
            "client": "pesterchum",
            "download": "https://raw.githubusercontent.com/mocchapi/pesterchum-themes/main/themes/pesterchum/UTChum.zip",
            "inherits": "pesterchum",
            "version": 0,
            "updated": 1455029682,
            "source": "https://github.com/mocchapi/pesterchum-themes",
            "description": "Undertale theme",
            "sha256_download": "a4af4fff76c8cff7b31a6160c9980d265ec8416cffab0770808ad206a7481010",
            "sha256_install": "06cbfbd4e326cde86ae665ece9018f2f7fd7d3ea1b6cb96945b7ae9d77cb42fb"
        },
        {
            "name": "strifekindBLU",
            "author": "Demadunk",
            "client": "pesterchum",
            "download": "https://raw.githubusercontent.com/mocchapi/pesterchum-themes/main/themes/pesterchum/strifekindBLU.zip",
            "inherits": "pesterchum2.5",
            "version": 0,
            "updated": 1451422446,
            "source": "https://github.com/mocchapi/pesterchum-themes",
            "description": "Strifekind, but blue",
            "sha256_download": "4ed8b5064b37b90cbf667e70557c7b403fa830c57ac0be403ba50a0aa480d1f7",
            "sha256_install": "499980ae860b3fc31db35e0eaba3f2c001691dbe897328d6a62ca8b3c63919b0"
        },
        {
            "name": "GalaxyChum",
            "author": "Demadunk",
            "client": "pesterchum",
            "download": "https://raw.githubusercontent.com/mocchapi/pesterchum-themes/main/themes/pesterchum/GalaxyChum.zip",
            "inherits": "",
            "version": 0,
            "updated": 1445580544,
            "source": "https://github.com/mocchapi/pesterchum-themes",
            "description": "Galaxy/space theme",
            "sha256_download": "cb3b84a9011488353fc3a23d24dcaf9645b5cd5c21671e0fa2da30175c747b58",
            "sha256_install": "a36eb68dc01f61a2df1ebd26526c7007b09f81a0f13b6a4cdde8983b2ac8f5bb"
        },
        {
            "name": "trollchum",
            "author": "catawump",
            "client": "pesterchum",
            "download": "https://raw.githubusercontent.com/mocchapi/pesterchum-themes/main/themes/pesterchum/trollchum.zip",
            "inherits": "",
            "version": 0,
            "updated": 1345405776,
            "source": "https://github.com/mocchapi/pesterchum-themes",
            "description": "A mix between trollian and pesterchum",
            "sha256_download": "0858187561d9582eb3d2deb6b8039bc4ed2fcce0f31808131f56e08f49716f0e",
            "sha256_install": "c5508a2011fabe869f9180391bfb89605e86d87479f995d79a3646daa3919ce4"
        },
        {
            "name": "HatsOff",
            "author": "Tristanlagreato",
            "client": "pesterchum",
            "download": "https://raw.githubusercontent.com/mocchapi/pesterchum-themes/main/themes/pesterchum/HatsOff.zip",
            "inherits": "",
            "version": 0,
            "updated": 1649551330,
            "source": "https://github.com/mocchapi/pesterchum-themes",
            "description": "Hats & squares!",
            "sha256_download": "92e99fda6577d458d8f841ad85ffb0b0b895adb364fe9da5fe85aa2900047cad",
            "sha256_install": "a68b337f8630db6c425e5b87c57fe5021cd910142122a99a1751b755aee3d842"
        },
        {
            "name": "MSN-1.0",
            "author": "jamie english",
            "client": "pesterchum",
            "download": "https://raw.githubusercontent.com/mocchapi/pesterchum-themes/main/themes/pesterchum/MSN-1.0.zip",
            "inherits": "",
            "version": 0,
            "updated": 1674001416,
            "source": "https://github.com/mocchapi/pesterchum-themes",
            "description": "MSN Messenger theme",
            "sha256_download": "d5667ea4f40d86338c63fcdf7bde9737a5014fbb899c7d4159e16674f968d6b1",
            "sha256_install": "902e94782d2c3cdf33d40fd702a818246f2824c6637b7492f8a7ab0a8d17397b"
        },
        {
            "name": "pibby the squeakwel",
            "author": "mal",
            "client": "pesterchum",
            "download": "https://raw.githubusercontent.com/mocchapi/pesterchum-themes/main/themes/pesterchum/pibby the squeakwel.zip",
            "inherits": "",
            "version": 0,
            "updated": 1696517391,
            "source": "https://github.com/mocchapi/pesterchum-themes",
            "description": "the long awaited sequel. critically acclaimed. finally available. for FREE. be thankful. there are not a lot of opportunities like this.",
            "sha256_download": "9ba18b3c869125fa36bda0e4421b0c9d0ac0e0a9db04c352dbe71639524963fd",
            "sha256_install": "20d6c410f4ceb82b01b432514563d89c971897a172b83ae2ca423dd41729e1bf"
        },
        {
            "name": "iChum",
            "author": "matytoonist",
            "client": "pesterchum",
            "download": "https://raw.githubusercontent.com/mocchapi/pesterchum-themes/main/themes/pesterchum/iChum.zip",
            "inherits": "",
            "version": 0,
            "updated": 1698067460,
            "source": "https://github.com/mocchapi/pesterchum-themes",
            "description": "Theme styled like a MacOS9 application",
            "sha256_download": "5ccdb9f8d7f0556aaa4bd94af50331284fc40eadf28aa80b836918c856acd31f",
            "sha256_install": "60c3983902078f53e8092919ae6c711226e6c947c56ea2e50841f6a85645d365"
        },
        {
            "name": "iChum (QT6 edition)",
            "author": "matytoonist",
            "client": "pesterchum",
            "download": "https://raw.githubusercontent.com/mocchapi/pesterchum-themes/main/themes/pesterchum/iChum (QT6 edition).zip",
            "inherits": "iChum",
            "version": 0,
            "updated": 1699045764,
            "source": "https://github.com/mocchapi/pesterchum-themes",
            "description": "Theme styled like a MacOS9 application (version for QT6)",
            "sha256_download": "bdb4d9c7f7a07c5fd3c6b38a91df0cad2fdb0c8c12c085c913bceb1c688bbbcf",
            "sha256_install": "3bd674c4ebb1267250c05f6cca2ae14113d0c9d3370248a141530b1eb7eb5725"
        },
        {
            "name": "intellichum compact",
            "author": "(lis)anne",
            "client": "pesterchum",
            "download": "https://raw.githubusercontent.com/mocchapi/pesterchum-themes/main/themes/pesterchum/intellichum compact.zip",
            "inherits": "Pesterchum",
            "version": 0,
            "updated": 1699045113,
            "source": "https://github.com/mocchapi/pesterchum-themes",
            "description": "As seen in HS^2 (smaller version)",
            "sha256_download": "91484d1e3e2eb801d107d2c2bf59840a417f6a312d4c47b8ef99c4a61995d4ec",
            "sha256_install": "c4a55e0c9d420380303d585040e4ae77e21ab8f8878b8ff6ba54e3cffcef3a75"
        },
        {
            "name": "intellichum",
            "author": "(lis)anne",
            "client": "pesterchum",
            "download": "https://raw.githubusercontent.com/mocchapi/pesterchum-themes/main/themes/pesterchum/intellichum.zip",
            "inherits": "intellichum compact",
            "version": 0,
            "updated": 1699042475,
            "source": "https://github.com/mocchapi/pesterchum-themes",
            "description": "As seen in HS^2",
            "sha256_download": "e57ec7231fc7446569038d7448dc0f988449576b91413cc6ad0ec66921221b85",
            "sha256_install": "7df8227b5336884a8a52533cd5a766746200bb108b3a934a8e8b5b4955217e42"
        },
        {
            "name": "intellichum compact light",
            "author": "(lis)anne",
            "client": "pesterchum",
            "download": "https://raw.githubusercontent.com/mocchapi/pesterchum-themes/main/themes/pesterchum/intellichum compact light.zip",
            "inherits": "intellichum compact",
            "version": 0,
            "updated": 1699045159,
            "source": "https://github.com/mocchapi/pesterchum-themes",
            "description": "Light mode version of intellichum compact",
            "sha256_download": "db334f828d34b5c43f1c810663d5119e67deaf0f4919efb76d687a254eb05568",
            "sha256_install": "4e26dd34d567b534aeb12b8f1f0584acc16b5c83912c1da6b98a36f142008a10"
        }
    ]
}